google_spacy_wrapper/__init__.py
google_spacy_wrapper/google_spacy.py
google_spacy_wrapper-0.0.5.dist-info/METADATA
google_spacy_wrapper-0.0.5.dist-info/WHEEL
google_spacy_wrapper-0.0.5.dist-info/top_level.txt
google_spacy_wrapper-0.0.5.dist-info/RECORD
