Metadata-Version: 2.1
Name: google-spacy-wrapper
Version: 0.0.5
Summary: Google Natural Language API Wrapper for Spacy
Author: PySlayer (Paul Antweiler)
Author-email: antweiler.paul@gmail.com
Keywords: python,nlp,natural language,google,google cloud,spacy,wrapper
Classifier: Development Status :: 1 - Planning
Classifier: Intended Audience :: Developers
Classifier: Programming Language :: Python :: 3
Classifier: Operating System :: Unix
Classifier: Operating System :: MacOS :: MacOS X
Classifier: Operating System :: Microsoft :: Windows
Requires-Dist: google-cloud-language
